setup.py
cellworld_experiment_service/__init__.py
cellworld_experiment_service/experiment_client.py
cellworld_experiment_service/experiment_messages.py
cellworld_experiment_service/experiment_service.py
cellworld_experiment_service.egg-info/PKG-INFO
cellworld_experiment_service.egg-info/SOURCES.txt
cellworld_experiment_service.egg-info/dependency_links.txt
cellworld_experiment_service.egg-info/not-zip-safe
cellworld_experiment_service.egg-info/requires.txt
cellworld_experiment_service.egg-info/top_level.txt