Metadata-Version: 1.0
Name: cellworld-experiment-service
Version: 0.0.1
Summary: experiment service
Home-page: UNKNOWN
Author: german espinosa
Author-email: germanespinosa@gmail.com
License: MIT
Platform: UNKNOWN
